{
    "directed":false,
    "graph":{},
    "links":[
        {
            "source":0,
            "target":128,
            "weight":1
        },
        {
            "source":0,
            "target":143,
            "weight":1
        },
        {
            "source":1,
            "target":67,
            "weight":1
        },
        {
            "source":1,
            "target":60,
            "weight":1
        },
        {
            "source":2,
            "target":134,
            "weight":1
        },
        {
            "source":3,
            "target":103,
            "weight":1
        },
        {
            "source":3,
            "target":43,
            "weight":1
        },
        {
            "source":3,
            "target":150,
            "weight":2
        },
        {
            "source":3,
            "target":78,
            "weight":1
        },
        {
            "source":4,
            "target":81,
            "weight":1
        },
        {
            "source":5,
            "target":38,
            "weight":1
        },
        {
            "source":5,
            "target":52,
            "weight":1
        },
        {
            "source":5,
            "target":68,
            "weight":1
        },
        {
            "source":5,
            "target":17,
            "weight":1
        },
        {
            "source":6,
            "target":140,
            "weight":1
        },
        {
            "source":7,
            "target":132,
            "weight":1
        },
        {
            "source":7,
            "target":24,
            "weight":1
        },
        {
            "source":7,
            "target":79,
            "weight":2
        },
        {
            "source":7,
            "target":121,
            "weight":1
        },
        {
            "source":8,
            "target":131,
            "weight":1
        },
        {
            "source":8,
            "target":72,
            "weight":1
        },
        {
            "source":8,
            "target":56,
            "weight":1
        },
        {
            "source":8,
            "target":48,
            "weight":1
        },
        {
            "source":8,
            "target":98,
            "weight":1
        },
        {
            "source":8,
            "target":70,
            "weight":1
        },
        {
            "source":8,
            "target":93,
            "weight":1
        },
        {
            "source":8,
            "target":51,
            "weight":1
        },
        {
            "source":8,
            "target":29,
            "weight":1
        },
        {
            "source":8,
            "target":82,
            "weight":1
        },
        {
            "source":9,
            "target":91,
            "weight":1
        },
        {
            "source":9,
            "target":85,
            "weight":1
        },
        {
            "source":9,
            "target":108,
            "weight":1
        },
        {
            "source":10,
            "target":96,
            "weight":2
        },
        {
            "source":10,
            "target":110,
            "weight":1
        },
        {
            "source":10,
            "target":90,
            "weight":4
        },
        {
            "source":10,
            "target":57,
            "weight":1
        },
        {
            "source":11,
            "target":58,
            "weight":1
        },
        {
            "source":12,
            "target":71,
            "weight":1
        },
        {
            "source":13,
            "target":117,
            "weight":1
        },
        {
            "source":13,
            "target":142,
            "weight":1
        },
        {
            "source":14,
            "target":118,
            "weight":2
        },
        {
            "source":14,
            "target":28,
            "weight":1
        },
        {
            "source":15,
            "target":123,
            "weight":1
        },
        {
            "source":15,
            "target":127,
            "weight":1
        },
        {
            "source":16,
            "target":109,
            "weight":1
        },
        {
            "source":16,
            "target":23,
            "weight":1
        },
        {
            "source":17,
            "target":38,
            "weight":2
        },
        {
            "source":17,
            "target":52,
            "weight":1
        },
        {
            "source":17,
            "target":68,
            "weight":1
        },
        {
            "source":18,
            "target":36,
            "weight":1
        },
        {
            "source":19,
            "target":45,
            "weight":1
        },
        {
            "source":20,
            "target":62,
            "weight":2
        },
        {
            "source":20,
            "target":120,
            "weight":1
        },
        {
            "source":21,
            "target":139,
            "weight":1
        },
        {
            "source":21,
            "target":148,
            "weight":1
        },
        {
            "source":22,
            "target":34,
            "weight":2
        },
        {
            "source":22,
            "target":84,
            "weight":1
        },
        {
            "source":22,
            "target":86,
            "weight":1
        },
        {
            "source":22,
            "target":100,
            "weight":1
        },
        {
            "source":22,
            "target":129,
            "weight":2
        },
        {
            "source":22,
            "target":55,
            "weight":2
        },
        {
            "source":22,
            "target":47,
            "weight":1
        },
        {
            "source":22,
            "target":130,
            "weight":1
        },
        {
            "source":22,
            "target":30,
            "weight":1
        },
        {
            "source":23,
            "target":65,
            "weight":1
        },
        {
            "source":23,
            "target":73,
            "weight":1
        },
        {
            "source":23,
            "target":109,
            "weight":3
        },
        {
            "source":23,
            "target":106,
            "weight":1
        },
        {
            "source":24,
            "target":104,
            "weight":1
        },
        {
            "source":24,
            "target":50,
            "weight":1
        },
        {
            "source":24,
            "target":136,
            "weight":1
        },
        {
            "source":24,
            "target":77,
            "weight":1
        },
        {
            "source":24,
            "target":101,
            "weight":1
        },
        {
            "source":24,
            "target":79,
            "weight":2
        },
        {
            "source":24,
            "target":121,
            "weight":1
        },
        {
            "source":25,
            "target":63,
            "weight":1
        },
        {
            "source":25,
            "target":61,
            "weight":1
        },
        {
            "source":26,
            "target":137,
            "weight":1
        },
        {
            "source":27,
            "target":151,
            "weight":2
        },
        {
            "source":27,
            "target":76,
            "weight":2
        },
        {
            "source":27,
            "target":121,
            "weight":2
        },
        {
            "source":27,
            "target":37,
            "weight":1
        },
        {
            "source":27,
            "target":149,
            "weight":4
        },
        {
            "source":27,
            "target":39,
            "weight":2
        },
        {
            "source":27,
            "target":40,
            "weight":1
        },
        {
            "source":27,
            "target":99,
            "weight":2
        },
        {
            "source":28,
            "target":118,
            "weight":1
        },
        {
            "source":29,
            "target":131,
            "weight":1
        },
        {
            "source":29,
            "target":72,
            "weight":1
        },
        {
            "source":29,
            "target":56,
            "weight":1
        },
        {
            "source":29,
            "target":48,
            "weight":1
        },
        {
            "source":29,
            "target":70,
            "weight":1
        },
        {
            "source":29,
            "target":93,
            "weight":1
        },
        {
            "source":29,
            "target":51,
            "weight":1
        },
        {
            "source":29,
            "target":82,
            "weight":1
        },
        {
            "source":30,
            "target":34,
            "weight":1
        },
        {
            "source":30,
            "target":84,
            "weight":1
        },
        {
            "source":30,
            "target":86,
            "weight":2
        },
        {
            "source":30,
            "target":100,
            "weight":1
        },
        {
            "source":30,
            "target":129,
            "weight":1
        },
        {
            "source":30,
            "target":55,
            "weight":1
        },
        {
            "source":30,
            "target":47,
            "weight":1
        },
        {
            "source":30,
            "target":130,
            "weight":1
        },
        {
            "source":31,
            "target":74,
            "weight":2
        },
        {
            "source":31,
            "target":69,
            "weight":1
        },
        {
            "source":32,
            "target":113,
            "weight":1
        },
        {
            "source":33,
            "target":66,
            "weight":2
        },
        {
            "source":33,
            "target":44,
            "weight":1
        },
        {
            "source":33,
            "target":67,
            "weight":1
        },
        {
            "source":33,
            "target":60,
            "weight":1
        },
        {
            "source":33,
            "target":135,
            "weight":1
        },
        {
            "source":33,
            "target":105,
            "weight":1
        },
        {
            "source":33,
            "target":147,
            "weight":1
        },
        {
            "source":33,
            "target":116,
            "weight":2
        },
        {
            "source":34,
            "target":130,
            "weight":1
        },
        {
            "source":34,
            "target":100,
            "weight":1
        },
        {
            "source":34,
            "target":55,
            "weight":2
        },
        {
            "source":34,
            "target":47,
            "weight":1
        },
        {
            "source":34,
            "target":84,
            "weight":1
        },
        {
            "source":34,
            "target":86,
            "weight":1
        },
        {
            "source":34,
            "target":129,
            "weight":1
        },
        {
            "source":35,
            "target":49,
            "weight":1
        },
        {
            "source":37,
            "target":151,
            "weight":1
        },
        {
            "source":37,
            "target":99,
            "weight":2
        },
        {
            "source":37,
            "target":39,
            "weight":2
        },
        {
            "source":37,
            "target":121,
            "weight":1
        },
        {
            "source":37,
            "target":149,
            "weight":1
        },
        {
            "source":37,
            "target":40,
            "weight":1
        },
        {
            "source":38,
            "target":68,
            "weight":1
        },
        {
            "source":38,
            "target":52,
            "weight":2
        },
        {
            "source":39,
            "target":151,
            "weight":3
        },
        {
            "source":39,
            "target":99,
            "weight":6
        },
        {
            "source":39,
            "target":76,
            "weight":1
        },
        {
            "source":39,
            "target":121,
            "weight":2
        },
        {
            "source":39,
            "target":149,
            "weight":2
        },
        {
            "source":39,
            "target":40,
            "weight":3
        },
        {
            "source":40,
            "target":151,
            "weight":1
        },
        {
            "source":40,
            "target":99,
            "weight":3
        },
        {
            "source":40,
            "target":149,
            "weight":2
        },
        {
            "source":40,
            "target":76,
            "weight":2
        },
        {
            "source":40,
            "target":121,
            "weight":2
        },
        {
            "source":41,
            "target":107,
            "weight":1
        },
        {
            "source":42,
            "target":128,
            "weight":1
        },
        {
            "source":43,
            "target":89,
            "weight":1
        },
        {
            "source":43,
            "target":103,
            "weight":1
        },
        {
            "source":43,
            "target":78,
            "weight":1
        },
        {
            "source":43,
            "target":150,
            "weight":1
        },
        {
            "source":44,
            "target":66,
            "weight":1
        },
        {
            "source":44,
            "target":116,
            "weight":1
        },
        {
            "source":45,
            "target":95,
            "weight":2
        },
        {
            "source":46,
            "target":126,
            "weight":1
        },
        {
            "source":47,
            "target":84,
            "weight":1
        },
        {
            "source":47,
            "target":86,
            "weight":1
        },
        {
            "source":47,
            "target":100,
            "weight":1
        },
        {
            "source":47,
            "target":129,
            "weight":1
        },
        {
            "source":47,
            "target":55,
            "weight":1
        },
        {
            "source":47,
            "target":130,
            "weight":1
        },
        {
            "source":48,
            "target":131,
            "weight":1
        },
        {
            "source":48,
            "target":72,
            "weight":1
        },
        {
            "source":48,
            "target":56,
            "weight":1
        },
        {
            "source":48,
            "target":70,
            "weight":1
        },
        {
            "source":48,
            "target":51,
            "weight":1
        },
        {
            "source":48,
            "target":82,
            "weight":1
        },
        {
            "source":48,
            "target":93,
            "weight":1
        },
        {
            "source":51,
            "target":131,
            "weight":1
        },
        {
            "source":51,
            "target":72,
            "weight":1
        },
        {
            "source":51,
            "target":56,
            "weight":1
        },
        {
            "source":51,
            "target":70,
            "weight":1
        },
        {
            "source":51,
            "target":93,
            "weight":1
        },
        {
            "source":51,
            "target":82,
            "weight":1
        },
        {
            "source":52,
            "target":68,
            "weight":1
        },
        {
            "source":53,
            "target":54,
            "weight":2
        },
        {
            "source":55,
            "target":84,
            "weight":1
        },
        {
            "source":55,
            "target":86,
            "weight":1
        },
        {
            "source":55,
            "target":100,
            "weight":1
        },
        {
            "source":55,
            "target":129,
            "weight":1
        },
        {
            "source":55,
            "target":130,
            "weight":1
        },
        {
            "source":56,
            "target":131,
            "weight":1
        },
        {
            "source":56,
            "target":72,
            "weight":1
        },
        {
            "source":56,
            "target":88,
            "weight":1
        },
        {
            "source":56,
            "target":70,
            "weight":1
        },
        {
            "source":56,
            "target":82,
            "weight":1
        },
        {
            "source":56,
            "target":93,
            "weight":1
        },
        {
            "source":57,
            "target":96,
            "weight":1
        },
        {
            "source":57,
            "target":90,
            "weight":1
        },
        {
            "source":59,
            "target":92,
            "weight":1
        },
        {
            "source":60,
            "target":66,
            "weight":1
        },
        {
            "source":60,
            "target":147,
            "weight":1
        },
        {
            "source":60,
            "target":105,
            "weight":1
        },
        {
            "source":60,
            "target":135,
            "weight":1
        },
        {
            "source":60,
            "target":67,
            "weight":2
        },
        {
            "source":60,
            "target":116,
            "weight":1
        },
        {
            "source":61,
            "target":63,
            "weight":3
        },
        {
            "source":64,
            "target":122,
            "weight":1
        },
        {
            "source":65,
            "target":109,
            "weight":1
        },
        {
            "source":65,
            "target":106,
            "weight":2
        },
        {
            "source":65,
            "target":73,
            "weight":1
        },
        {
            "source":66,
            "target":67,
            "weight":1
        },
        {
            "source":66,
            "target":135,
            "weight":1
        },
        {
            "source":66,
            "target":105,
            "weight":1
        },
        {
            "source":66,
            "target":147,
            "weight":1
        },
        {
            "source":66,
            "target":116,
            "weight":2
        },
        {
            "source":67,
            "target":147,
            "weight":1
        },
        {
            "source":67,
            "target":105,
            "weight":1
        },
        {
            "source":67,
            "target":135,
            "weight":1
        },
        {
            "source":67,
            "target":116,
            "weight":1
        },
        {
            "source":69,
            "target":74,
            "weight":1
        },
        {
            "source":70,
            "target":131,
            "weight":2
        },
        {
            "source":70,
            "target":72,
            "weight":2
        },
        {
            "source":70,
            "target":94,
            "weight":1
        },
        {
            "source":70,
            "target":146,
            "weight":1
        },
        {
            "source":70,
            "target":145,
            "weight":1
        },
        {
            "source":70,
            "target":82,
            "weight":1
        },
        {
            "source":70,
            "target":93,
            "weight":1
        },
        {
            "source":72,
            "target":131,
            "weight":2
        },
        {
            "source":72,
            "target":145,
            "weight":1
        },
        {
            "source":72,
            "target":146,
            "weight":1
        },
        {
            "source":72,
            "target":82,
            "weight":1
        },
        {
            "source":72,
            "target":93,
            "weight":1
        },
        {
            "source":72,
            "target":94,
            "weight":1
        },
        {
            "source":73,
            "target":109,
            "weight":1
        },
        {
            "source":73,
            "target":106,
            "weight":1
        },
        {
            "source":75,
            "target":141,
            "weight":3
        },
        {
            "source":76,
            "target":151,
            "weight":1
        },
        {
            "source":76,
            "target":99,
            "weight":1
        },
        {
            "source":76,
            "target":149,
            "weight":3
        },
        {
            "source":76,
            "target":121,
            "weight":2
        },
        {
            "source":78,
            "target":103,
            "weight":1
        },
        {
            "source":78,
            "target":150,
            "weight":1
        },
        {
            "source":79,
            "target":104,
            "weight":1
        },
        {
            "source":79,
            "target":132,
            "weight":1
        },
        {
            "source":79,
            "target":121,
            "weight":1
        },
        {
            "source":80,
            "target":83,
            "weight":1
        },
        {
            "source":82,
            "target":131,
            "weight":1
        },
        {
            "source":82,
            "target":93,
            "weight":1
        },
        {
            "source":84,
            "target":130,
            "weight":1
        },
        {
            "source":84,
            "target":100,
            "weight":1
        },
        {
            "source":84,
            "target":86,
            "weight":1
        },
        {
            "source":84,
            "target":129,
            "weight":1
        },
        {
            "source":85,
            "target":91,
            "weight":1
        },
        {
            "source":85,
            "target":108,
            "weight":1
        },
        {
            "source":86,
            "target":130,
            "weight":1
        },
        {
            "source":86,
            "target":100,
            "weight":1
        },
        {
            "source":86,
            "target":129,
            "weight":1
        },
        {
            "source":87,
            "target":102,
            "weight":1
        },
        {
            "source":89,
            "target":114,
            "weight":1
        },
        {
            "source":89,
            "target":103,
            "weight":1
        },
        {
            "source":89,
            "target":148,
            "weight":1
        },
        {
            "source":90,
            "target":96,
            "weight":2
        },
        {
            "source":90,
            "target":110,
            "weight":1
        },
        {
            "source":91,
            "target":108,
            "weight":2
        },
        {
            "source":93,
            "target":131,
            "weight":1
        },
        {
            "source":94,
            "target":131,
            "weight":1
        },
        {
            "source":94,
            "target":145,
            "weight":1
        },
        {
            "source":94,
            "target":146,
            "weight":1
        },
        {
            "source":96,
            "target":110,
            "weight":1
        },
        {
            "source":97,
            "target":112,
            "weight":1
        },
        {
            "source":97,
            "target":125,
            "weight":1
        },
        {
            "source":99,
            "target":151,
            "weight":3
        },
        {
            "source":99,
            "target":121,
            "weight":2
        },
        {
            "source":99,
            "target":149,
            "weight":2
        },
        {
            "source":100,
            "target":130,
            "weight":1
        },
        {
            "source":100,
            "target":129,
            "weight":1
        },
        {
            "source":103,
            "target":150,
            "weight":1
        },
        {
            "source":105,
            "target":147,
            "weight":1
        },
        {
            "source":105,
            "target":135,
            "weight":1
        },
        {
            "source":105,
            "target":116,
            "weight":1
        },
        {
            "source":106,
            "target":109,
            "weight":1
        },
        {
            "source":111,
            "target":119,
            "weight":1
        },
        {
            "source":112,
            "target":125,
            "weight":1
        },
        {
            "source":114,
            "target":148,
            "weight":1
        },
        {
            "source":115,
            "target":144,
            "weight":1
        },
        {
            "source":116,
            "target":147,
            "weight":1
        },
        {
            "source":116,
            "target":135,
            "weight":1
        },
        {
            "source":117,
            "target":142,
            "weight":1
        },
        {
            "source":121,
            "target":151,
            "weight":2
        },
        {
            "source":121,
            "target":149,
            "weight":3
        },
        {
            "source":123,
            "target":127,
            "weight":1
        },
        {
            "source":124,
            "target":138,
            "weight":1
        },
        {
            "source":129,
            "target":130,
            "weight":1
        },
        {
            "source":131,
            "target":145,
            "weight":1
        },
        {
            "source":131,
            "target":146,
            "weight":1
        },
        {
            "source":133,
            "target":140,
            "weight":1
        },
        {
            "source":135,
            "target":147,
            "weight":1
        },
        {
            "source":139,
            "target":148,
            "weight":1
        },
        {
            "source":145,
            "target":146,
            "weight":1
        },
        {
            "source":149,
            "target":151,
            "weight":2
        }
    ],
    "multigraph":false,
    "nodes":[
        {
            "betweenness":0.00017660044150110375,
            "degree":0.013245033112582781,
            "eigenvector":1.8572710010312663e-19,
            "group":0,
            "id":0,
            "name":"caadria2005_a_8a_b"
        },
        {
            "betweenness":1.1037527593818985e-05,
            "degree":0.013245033112582781,
            "eigenvector":5.337244933342577e-08,
            "group":1,
            "id":1,
            "name":"102caadria2004"
        },
        {
            "betweenness":0.0,
            "degree":0.006622516556291391,
            "eigenvector":4.242176492992784e-22,
            "group":2,
            "id":2,
            "name":"105caadria2004"
        },
        {
            "betweenness":0.0,
            "degree":0.026490066225165563,
            "eigenvector":3.855288419136399e-12,
            "group":3,
            "id":3,
            "name":"306caadria2004"
        },
        {
            "betweenness":0.0,
            "degree":0.006622516556291391,
            "eigenvector":4.242176492992784e-22,
            "group":4,
            "id":4,
            "name":"308caadria2004"
        },
        {
            "betweenness":5.886681383370125e-05,
            "degree":0.026490066225165563,
            "eigenvector":7.700947338543973e-12,
            "group":5,
            "id":5,
            "name":"caadria2003_b4-2"
        },
        {
            "betweenness":0.0,
            "degree":0.006622516556291391,
            "eigenvector":2.2762743141225855e-20,
            "group":6,
            "id":6,
            "name":"caadria2003_b2-2"
        },
        {
            "betweenness":0.0008388520971302428,
            "degree":0.026490066225165563,
            "eigenvector":0.02395117616391141,
            "group":7,
            "id":7,
            "name":"caadria2005_a_1a_e"
        },
        {
            "betweenness":0.0011719847481436885,
            "degree":0.06622516556291391,
            "eigenvector":1.106977238035523e-05,
            "group":8,
            "id":8,
            "name":"caadria2005_b_6a_b"
        },
        {
            "betweenness":2.9433406916850625e-05,
            "degree":0.019867549668874173,
            "eigenvector":2.7658162220120038e-14,
            "group":9,
            "id":9,
            "name":"403caadria2004"
        },
        {
            "betweenness":2.9433406916850625e-05,
            "degree":0.026490066225165563,
            "eigenvector":1.5895656574177973e-09,
            "group":10,
            "id":10,
            "name":"511caadria2004"
        },
        {
            "betweenness":0.0,
            "degree":0.006622516556291391,
            "eigenvector":4.242176492992784e-22,
            "group":11,
            "id":11,
            "name":"caadria2003_a4-3"
        },
        {
            "betweenness":0.0,
            "degree":0.006622516556291391,
            "eigenvector":4.242176492992784e-22,
            "group":12,
            "id":12,
            "name":"caadria2005_a_7c_d"
        },
        {
            "betweenness":0.0,
            "degree":0.013245033112582781,
            "eigenvector":3.173923335039738e-18,
            "group":13,
            "id":13,
            "name":"caadria2005_a_2c_f"
        },
        {
            "betweenness":0.0,
            "degree":0.013245033112582781,
            "eigenvector":4.1699591327003924e-16,
            "group":14,
            "id":14,
            "name":"caadria2005_b_3a_c"
        },
        {
            "betweenness":0.0,
            "degree":0.013245033112582781,
            "eigenvector":3.173923335039738e-18,
            "group":15,
            "id":15,
            "name":"caadria2003_b4-3"
        },
        {
            "betweenness":2.207505518763797e-05,
            "degree":0.013245033112582781,
            "eigenvector":3.509514394596732e-11,
            "group":16,
            "id":16,
            "name":"caadria2005_b_5c_d"
        },
        {
            "betweenness":0.0,
            "degree":0.026490066225165563,
            "eigenvector":9.554405968694722e-12,
            "group":5,
            "id":17,
            "name":"505caadria2004"
        },
        {
            "betweenness":0.0,
            "degree":0.006622516556291391,
            "eigenvector":4.242176492992784e-22,
            "group":17,
            "id":18,
            "name":"caadria2005_a_8b_c"
        },
        {
            "betweenness":0.0,
            "degree":0.006622516556291391,
            "eigenvector":8.796746862970011e-18,
            "group":18,
            "id":19,
            "name":"caadria2003_c2-2"
        },
        {
            "betweenness":8.830022075055188e-05,
            "degree":0.013245033112582781,
            "eigenvector":1.967012396270894e-17,
            "group":19,
            "id":20,
            "name":"caadria2003_a2-2"
        },
        {
            "betweenness":0.0,
            "degree":0.013245033112582781,
            "eigenvector":1.5023482481305245e-13,
            "group":3,
            "id":21,
            "name":"516caadria2004"
        },
        {
            "betweenness":9.811135638950207e-06,
            "degree":0.059602649006622516,
            "eigenvector":1.1841554663078936e-05,
            "group":21,
            "id":22,
            "name":"caadria2005_b_5a_c"
        },
        {
            "betweenness":0.00015452538631346578,
            "degree":0.033112582781456956,
            "eigenvector":9.659349393160845e-11,
            "group":16,
            "id":23,
            "name":"caadria2005_b_4b_a"
        },
        {
            "betweenness":0.005607064017660044,
            "degree":0.052980132450331126,
            "eigenvector":0.024276561190515678,
            "group":7,
            "id":24,
            "name":"501caadria2004"
        },
        {
            "betweenness":8.830022075055188e-05,
            "degree":0.013245033112582781,
            "eigenvector":1.9892402824204374e-14,
            "group":23,
            "id":25,
            "name":"caadria2003_b5-1"
        },
        {
            "betweenness":0.0,
            "degree":0.006622516556291391,
            "eigenvector":4.242176492992784e-22,
            "group":24,
            "id":26,
            "name":"caadria2005_b_4b_d"
        },
        {
            "betweenness":3.532008830022075e-05,
            "degree":0.052980132450331126,
            "eigenvector":0.3236034914119693,
            "group":25,
            "id":27,
            "name":"309caadria2004"
        },
        {
            "betweenness":4.415011037527594e-05,
            "degree":0.013245033112582781,
            "eigenvector":3.0526219506225375e-16,
            "group":14,
            "id":28,
            "name":"caadria2005_b_3c_b"
        },
        {
            "betweenness":2.4081878386514145e-05,
            "degree":0.059602649006622516,
            "eigenvector":1.0972341274946868e-05,
            "group":8,
            "id":29,
            "name":"caadria2005_b_4c_f"
        },
        {
            "betweenness":4.8880479344055496e-05,
            "degree":0.059602649006622516,
            "eigenvector":9.840848032777072e-06,
            "group":21,
            "id":30,
            "name":"caadria2005_b_5a_a"
        },
        {
            "betweenness":0.0,
            "degree":0.013245033112582781,
            "eigenvector":4.1699591327003924e-16,
            "group":26,
            "id":31,
            "name":"caadria2005_a_7b_b"
        },
        {
            "betweenness":0.0,
            "degree":0.006622516556291391,
            "eigenvector":4.242176492992784e-22,
            "group":27,
            "id":32,
            "name":"510caadria2004"
        },
        {
            "betweenness":0.00018763796909492276,
            "degree":0.052980132450331126,
            "eigenvector":2.5786274891102345e-07,
            "group":1,
            "id":33,
            "name":"caadria2003_b2-3"
        },
        {
            "betweenness":9.811135638950207e-06,
            "degree":0.059602649006622516,
            "eigenvector":1.1013332938054619e-05,
            "group":21,
            "id":34,
            "name":"caadria2003_b1-4"
        },
        {
            "betweenness":0.0,
            "degree":0.006622516556291391,
            "eigenvector":4.242176492992784e-22,
            "group":28,
            "id":35,
            "name":"caadria2003_b3-2"
        },
        {
            "betweenness":0.0,
            "degree":0.006622516556291391,
            "eigenvector":4.242176492992784e-22,
            "group":17,
            "id":36,
            "name":"111caadria2004"
        },
        {
            "betweenness":0.0024665194996320826,
            "degree":0.046357615894039736,
            "eigenvector":0.19803906712953603,
            "group":25,
            "id":37,
            "name":"caadria2005_a_2b_b"
        },
        {
            "betweenness":0.0,
            "degree":0.026490066225165563,
            "eigenvector":1.0938741431923081e-11,
            "group":5,
            "id":38,
            "name":"caadria2005_b_5c_f"
        },
        {
            "betweenness":1.7660044150110377e-05,
            "degree":0.052980132450331126,
            "eigenvector":0.4216397517309733,
            "group":25,
            "id":39,
            "name":"517caadria2004"
        },
        {
            "betweenness":2.9433406916850625e-05,
            "degree":0.052980132450331126,
            "eigenvector":0.31207747074319625,
            "group":25,
            "id":40,
            "name":"caadria2005_b_3a_d"
        },
        {
            "betweenness":0.0,
            "degree":0.006622516556291391,
            "eigenvector":4.242176492992784e-22,
            "group":29,
            "id":41,
            "name":"caadria2005_a_1b_b"
        },
        {
            "betweenness":0.0,
            "degree":0.006622516556291391,
            "eigenvector":1.1478566049568635e-19,
            "group":0,
            "id":42,
            "name":"caadria2005_a_2a_c"
        },
        {
            "betweenness":0.000684326710816777,
            "degree":0.033112582781456956,
            "eigenvector":3.47704039020304e-12,
            "group":3,
            "id":43,
            "name":"caadria2005_a_2a_d"
        },
        {
            "betweenness":3.784295175023652e-05,
            "degree":0.019867549668874173,
            "eigenvector":9.293701053078126e-08,
            "group":1,
            "id":44,
            "name":"caadria2005_a_2a_b"
        },
        {
            "betweenness":8.830022075055188e-05,
            "degree":0.013245033112582781,
            "eigenvector":1.9670123962708935e-17,
            "group":18,
            "id":45,
            "name":"107caadria2004"
        },
        {
            "betweenness":0.0,
            "degree":0.006622516556291391,
            "eigenvector":4.242176492992784e-22,
            "group":31,
            "id":46,
            "name":"209caadria2004"
        },
        {
            "betweenness":5.869161498300571e-05,
            "degree":0.059602649006622516,
            "eigenvector":8.95424816400024e-06,
            "group":21,
            "id":47,
            "name":"212caadria2004"
        },
        {
            "betweenness":2.4081878386514145e-05,
            "degree":0.059602649006622516,
            "eigenvector":1.0972341274946868e-05,
            "group":8,
            "id":48,
            "name":"301caadria2004"
        },
        {
            "betweenness":0.0,
            "degree":0.006622516556291391,
            "eigenvector":4.242176492992784e-22,
            "group":28,
            "id":49,
            "name":"caadria2003_a6-4"
        },
        {
            "betweenness":0.0,
            "degree":0.006622516556291391,
            "eigenvector":0.0014440527148702757,
            "group":7,
            "id":50,
            "name":"302caadria2004"
        },
        {
            "betweenness":2.4081878386514145e-05,
            "degree":0.059602649006622516,
            "eigenvector":1.0972341274946868e-05,
            "group":8,
            "id":51,
            "name":"caadria2005_a_8c_a"
        },
        {
            "betweenness":0.0,
            "degree":0.026490066225165563,
            "eigenvector":9.554405968694722e-12,
            "group":5,
            "id":52,
            "name":"caadria2005_b_5c_e"
        },
        {
            "betweenness":0.0,
            "degree":0.006622516556291391,
            "eigenvector":3.173923335039738e-18,
            "group":32,
            "id":53,
            "name":"caadria2003_a5-1"
        },
        {
            "betweenness":0.0,
            "degree":0.006622516556291391,
            "eigenvector":3.173923335039738e-18,
            "group":32,
            "id":54,
            "name":"caadria2005_b_5b_d"
        },
        {
            "betweenness":9.811135638950207e-06,
            "degree":0.059602649006622516,
            "eigenvector":1.1013332938054619e-05,
            "group":21,
            "id":55,
            "name":"207caadria2004"
        },
        {
            "betweenness":0.0011719847481436885,
            "degree":0.06622516556291391,
            "eigenvector":1.106977238035523e-05,
            "group":8,
            "id":56,
            "name":"210caadria2004"
        },
        {
            "betweenness":0.00010301692420897718,
            "degree":0.019867549668874173,
            "eigenvector":6.872017297451429e-10,
            "group":10,
            "id":57,
            "name":"caadria2004_k-1"
        },
        {
            "betweenness":0.0,
            "degree":0.006622516556291391,
            "eigenvector":4.242176492992784e-22,
            "group":11,
            "id":58,
            "name":"caadria2003_a5-4"
        },
        {
            "betweenness":0.0,
            "degree":0.006622516556291391,
            "eigenvector":4.242176492992784e-22,
            "group":33,
            "id":59,
            "name":"515caadria2004"
        },
        {
            "betweenness":0.00034689372437716803,
            "degree":0.052980132450331126,
            "eigenvector":2.2213055524290713e-07,
            "group":1,
            "id":60,
            "name":"caadria2005_a_1b_c"
        },
        {
            "betweenness":0.0,
            "degree":0.013245033112582781,
            "eigenvector":3.54239216160357e-14,
            "group":23,
            "id":61,
            "name":"caadria2005_a_7b_d"
        },
        {
            "betweenness":0.0,
            "degree":0.006622516556291391,
            "eigenvector":1.7593493725838885e-17,
            "group":19,
            "id":62,
            "name":"caadria2005_a_1b_d"
        },
        {
            "betweenness":0.0,
            "degree":0.013245033112582781,
            "eigenvector":3.54239216160357e-14,
            "group":23,
            "id":63,
            "name":"caadria2003_a1-1"
        },
        {
            "betweenness":0.0,
            "degree":0.006622516556291391,
            "eigenvector":4.242176492992784e-22,
            "group":34,
            "id":64,
            "name":"caadria2005_b_3c_e"
        },
        {
            "betweenness":2.207505518763797e-05,
            "degree":0.026490066225165563,
            "eigenvector":7.267039355365317e-11,
            "group":16,
            "id":65,
            "name":"caadria2003_a4-1"
        },
        {
            "betweenness":0.00018763796909492276,
            "degree":0.052980132450331126,
            "eigenvector":2.5786274891102345e-07,
            "group":1,
            "id":66,
            "name":"204caadria2004"
        },
        {
            "betweenness":0.00034689372437716803,
            "degree":0.052980132450331126,
            "eigenvector":2.2213055524290713e-07,
            "group":1,
            "id":67,
            "name":"caadria2005_b_5b_a"
        },
        {
            "betweenness":5.886681383370125e-05,
            "degree":0.026490066225165563,
            "eigenvector":7.700947338543973e-12,
            "group":5,
            "id":68,
            "name":"514caadria2004"
        },
        {
            "betweenness":4.415011037527594e-05,
            "degree":0.013245033112582781,
            "eigenvector":3.0526219506225375e-16,
            "group":26,
            "id":69,
            "name":"caadria2005_b_5b_b"
        },
        {
            "betweenness":0.0007947019867549669,
            "degree":0.07947019867549669,
            "eigenvector":1.5189601138661223e-05,
            "group":8,
            "id":70,
            "name":"caadria2005_a_2a_a"
        },
        {
            "betweenness":0.0,
            "degree":0.006622516556291391,
            "eigenvector":4.242176492992784e-22,
            "group":12,
            "id":71,
            "name":"caadria2003_c1-1"
        },
        {
            "betweenness":0.0007947019867549669,
            "degree":0.07947019867549669,
            "eigenvector":1.5189601138661223e-05,
            "group":8,
            "id":72,
            "name":"caadria2003_a5-3"
        },
        {
            "betweenness":4.415011037527594e-05,
            "degree":0.026490066225165563,
            "eigenvector":6.149834998564114e-11,
            "group":16,
            "id":73,
            "name":"caadria2003_b7-3"
        },
        {
            "betweenness":0.0,
            "degree":0.013245033112582781,
            "eigenvector":4.1699591327003924e-16,
            "group":26,
            "id":74,
            "name":"caadria2003_b3-4"
        },
        {
            "betweenness":0.0,
            "degree":0.006622516556291391,
            "eigenvector":1.7792977833265605e-15,
            "group":35,
            "id":75,
            "name":"caadria2005_b_3c_d"
        },
        {
            "betweenness":0.0003355408388520971,
            "degree":0.046357615894039736,
            "eigenvector":0.24856001568752836,
            "group":25,
            "id":76,
            "name":"caadria2005_b_3a_b"
        },
        {
            "betweenness":0.0,
            "degree":0.006622516556291391,
            "eigenvector":0.0014440527148702757,
            "group":7,
            "id":77,
            "name":"312caadria2004"
        },
        {
            "betweenness":2.207505518763797e-05,
            "degree":0.026490066225165563,
            "eigenvector":3.1700309036542623e-12,
            "group":3,
            "id":78,
            "name":"caadria2005_a_2b_a"
        },
        {
            "betweenness":0.0008830022075055188,
            "degree":0.033112582781456956,
            "eigenvector":0.0253987774301514,
            "group":7,
            "id":79,
            "name":"caadria2005_a_7c_b"
        },
        {
            "betweenness":0.0,
            "degree":0.006622516556291391,
            "eigenvector":4.242176492992784e-22,
            "group":36,
            "id":80,
            "name":"202caadria2004"
        },
        {
            "betweenness":0.0,
            "degree":0.006622516556291391,
            "eigenvector":4.242176492992784e-22,
            "group":4,
            "id":81,
            "name":"402caadria2004"
        },
        {
            "betweenness":2.4081878386514145e-05,
            "degree":0.059602649006622516,
            "eigenvector":1.0972341274946866e-05,
            "group":8,
            "id":82,
            "name":"caadria2005_b_6a_d"
        },
        {
            "betweenness":0.0,
            "degree":0.006622516556291391,
            "eigenvector":4.242176492992784e-22,
            "group":36,
            "id":83,
            "name":"caadria2005_a_1a_c"
        },
        {
            "betweenness":5.869161498300571e-05,
            "degree":0.059602649006622516,
            "eigenvector":8.95424816400024e-06,
            "group":21,
            "id":84,
            "name":"caadria2003_b4-4"
        },
        {
            "betweenness":2.9433406916850625e-05,
            "degree":0.019867549668874173,
            "eigenvector":2.7658162220120038e-14,
            "group":9,
            "id":85,
            "name":"caadria2003_b5-3"
        },
        {
            "betweenness":4.8880479344055496e-05,
            "degree":0.059602649006622516,
            "eigenvector":9.84084803277707e-06,
            "group":21,
            "id":86,
            "name":"caadria2003_b5-4"
        },
        {
            "betweenness":0.0,
            "degree":0.006622516556291391,
            "eigenvector":4.242176492992784e-22,
            "group":37,
            "id":87,
            "name":"caadria2003_b2-1"
        },
        {
            "betweenness":0.0,
            "degree":0.006622516556291391,
            "eigenvector":1.088385387273917e-06,
            "group":8,
            "id":88,
            "name":"caadria2003_b4-1"
        },
        {
            "betweenness":0.0017660044150110375,
            "degree":0.026490066225165563,
            "eigenvector":1.7271808252858757e-12,
            "group":3,
            "id":89,
            "name":"201caadria2004"
        },
        {
            "betweenness":2.9433406916850625e-05,
            "degree":0.026490066225165563,
            "eigenvector":1.5895656574177975e-09,
            "group":10,
            "id":90,
            "name":"509caadria2004"
        },
        {
            "betweenness":0.0,
            "degree":0.019867549668874173,
            "eigenvector":3.542392161603571e-14,
            "group":9,
            "id":91,
            "name":"caadria2003_b1-3"
        },
        {
            "betweenness":0.0,
            "degree":0.006622516556291391,
            "eigenvector":4.242176492992784e-22,
            "group":33,
            "id":92,
            "name":"404caadria2004"
        },
        {
            "betweenness":2.4081878386514145e-05,
            "degree":0.059602649006622516,
            "eigenvector":1.0972341274946866e-05,
            "group":8,
            "id":93,
            "name":"caadria2005_a_8a_c"
        },
        {
            "betweenness":2.4081878386514145e-05,
            "degree":0.033112582781456956,
            "eigenvector":5.577016846354064e-06,
            "group":8,
            "id":94,
            "name":"115caadria2004"
        },
        {
            "betweenness":0.0,
            "degree":0.006622516556291391,
            "eigenvector":1.759349372583888e-17,
            "group":18,
            "id":95,
            "name":"caadria2003_a1-2"
        },
        {
            "betweenness":2.9433406916850625e-05,
            "degree":0.026490066225165563,
            "eigenvector":1.2105451423998542e-09,
            "group":10,
            "id":96,
            "name":"caadria2003_c5-3"
        },
        {
            "betweenness":0.0,
            "degree":0.013245033112582781,
            "eigenvector":3.173923335039738e-18,
            "group":38,
            "id":97,
            "name":"caadria2003_b1-1"
        },
        {
            "betweenness":0.0,
            "degree":0.006622516556291391,
            "eigenvector":1.088385387273917e-06,
            "group":8,
            "id":98,
            "name":"504caadria2004"
        },
        {
            "betweenness":1.7660044150110377e-05,
            "degree":0.052980132450331126,
            "eigenvector":0.4216397517309733,
            "group":25,
            "id":99,
            "name":"313caadria2004"
        },
        {
            "betweenness":5.869161498300571e-05,
            "degree":0.059602649006622516,
            "eigenvector":8.95424816400024e-06,
            "group":21,
            "id":100,
            "name":"110caadria2004"
        },
        {
            "betweenness":0.0,
            "degree":0.006622516556291391,
            "eigenvector":0.0014440527148702757,
            "group":7,
            "id":101,
            "name":"314caadria2004"
        },
        {
            "betweenness":0.0,
            "degree":0.006622516556291391,
            "eigenvector":4.242176492992784e-22,
            "group":37,
            "id":102,
            "name":"caadria2003_a6-2"
        },
        {
            "betweenness":0.000684326710816777,
            "degree":0.033112582781456956,
            "eigenvector":3.47704039020304e-12,
            "group":3,
            "id":103,
            "name":"caadria2005_a_1b_e"
        },
        {
            "betweenness":0.00014716703458425315,
            "degree":0.013245033112582781,
            "eigenvector":0.0029548586817775913,
            "group":7,
            "id":104,
            "name":"caadria2003_a3-4"
        },
        {
            "betweenness":4.88804793440555e-05,
            "degree":0.046357615894039736,
            "eigenvector":1.925821659455681e-07,
            "group":1,
            "id":105,
            "name":"410caadria2004"
        },
        {
            "betweenness":2.207505518763797e-05,
            "degree":0.026490066225165563,
            "eigenvector":7.267039355365317e-11,
            "group":16,
            "id":106,
            "name":"caadria2005_a_8b_a"
        },
        {
            "betweenness":0.0,
            "degree":0.006622516556291391,
            "eigenvector":4.242176492992784e-22,
            "group":29,
            "id":107,
            "name":"caadria2003_b6-2"
        },
        {
            "betweenness":0.0,
            "degree":0.019867549668874173,
            "eigenvector":3.542392161603571e-14,
            "group":9,
            "id":108,
            "name":"203caadria2004"
        },
        {
            "betweenness":0.00015452538631346578,
            "degree":0.033112582781456956,
            "eigenvector":9.659349393160846e-11,
            "group":16,
            "id":109,
            "name":"512caadria2004"
        },
        {
            "betweenness":0.00010301692420897718,
            "degree":0.019867549668874173,
            "eigenvector":6.872017297451429e-10,
            "group":10,
            "id":110,
            "name":"108caadria2004"
        },
        {
            "betweenness":0.0,
            "degree":0.006622516556291391,
            "eigenvector":4.242176492992784e-22,
            "group":30,
            "id":111,
            "name":"caadria2003_b3-3"
        },
        {
            "betweenness":0.0,
            "degree":0.013245033112582781,
            "eigenvector":3.173923335039738e-18,
            "group":38,
            "id":112,
            "name":"114caadria2004"
        },
        {
            "betweenness":0.0,
            "degree":0.006622516556291391,
            "eigenvector":4.242176492992784e-22,
            "group":27,
            "id":113,
            "name":"503caadria2004"
        },
        {
            "betweenness":0.0,
            "degree":0.013245033112582781,
            "eigenvector":4.911218753985843e-13,
            "group":3,
            "id":114,
            "name":"caadria2003_a3-3"
        },
        {
            "betweenness":0.0,
            "degree":0.006622516556291391,
            "eigenvector":4.242176492992784e-22,
            "group":20,
            "id":115,
            "name":"caadria2005_b_6c_d"
        },
        {
            "betweenness":0.00018763796909492276,
            "degree":0.052980132450331126,
            "eigenvector":2.5786274891102345e-07,
            "group":1,
            "id":116,
            "name":"caadria2005_a_7a_d"
        },
        {
            "betweenness":0.0,
            "degree":0.013245033112582781,
            "eigenvector":3.173923335039738e-18,
            "group":13,
            "id":117,
            "name":"caadria2003_b1-2"
        },
        {
            "betweenness":0.0,
            "degree":0.013245033112582781,
            "eigenvector":4.1699591327003924e-16,
            "group":14,
            "id":118,
            "name":"408caadria2004"
        },
        {
            "betweenness":0.0,
            "degree":0.006622516556291391,
            "eigenvector":4.242176492992784e-22,
            "group":30,
            "id":119,
            "name":"411caadria2004"
        },
        {
            "betweenness":0.0,
            "degree":0.006622516556291391,
            "eigenvector":8.796746862970013e-18,
            "group":19,
            "id":120,
            "name":"412caadria2004"
        },
        {
            "betweenness":0.006534216335540839,
            "degree":0.0728476821192053,
            "eigenvector":0.3246434053131035,
            "group":25,
            "id":121,
            "name":"caadria2005_b_4b_c"
        },
        {
            "betweenness":0.0,
            "degree":0.006622516556291391,
            "eigenvector":4.242176492992784e-22,
            "group":34,
            "id":122,
            "name":"caadria2005_a_7c_c"
        },
        {
            "betweenness":0.0,
            "degree":0.013245033112582781,
            "eigenvector":3.173923335039738e-18,
            "group":15,
            "id":123,
            "name":"113caadria2004"
        },
        {
            "betweenness":0.0,
            "degree":0.006622516556291391,
            "eigenvector":4.242176492992784e-22,
            "group":22,
            "id":124,
            "name":"caadria2003_c2-3"
        },
        {
            "betweenness":0.0,
            "degree":0.013245033112582781,
            "eigenvector":3.173923335039738e-18,
            "group":38,
            "id":125,
            "name":"518caadria2004"
        },
        {
            "betweenness":0.0,
            "degree":0.006622516556291391,
            "eigenvector":4.242176492992784e-22,
            "group":31,
            "id":126,
            "name":"caadria2005_b_4c_a"
        },
        {
            "betweenness":0.0,
            "degree":0.013245033112582781,
            "eigenvector":3.173923335039738e-18,
            "group":15,
            "id":127,
            "name":"caadria2005_b_3b_c"
        },
        {
            "betweenness":0.00017660044150110375,
            "degree":0.013245033112582781,
            "eigenvector":1.8572710010312663e-19,
            "group":0,
            "id":128,
            "name":"401caadria2004"
        },
        {
            "betweenness":2.0848663232769192e-05,
            "degree":0.059602649006622516,
            "eigenvector":1.0021099392210572e-05,
            "group":21,
            "id":129,
            "name":"206caadria2004"
        },
        {
            "betweenness":5.869161498300571e-05,
            "degree":0.059602649006622516,
            "eigenvector":8.95424816400024e-06,
            "group":21,
            "id":130,
            "name":"caadria2005_a_8c_c"
        },
        {
            "betweenness":0.0007947019867549669,
            "degree":0.07947019867549669,
            "eigenvector":1.5189601138661223e-05,
            "group":8,
            "id":131,
            "name":"caadria2003_a3-2"
        },
        {
            "betweenness":2.9433406916850625e-05,
            "degree":0.013245033112582781,
            "eigenvector":0.002935503669760655,
            "group":7,
            "id":132,
            "name":"316caadria2004"
        },
        {
            "betweenness":0.0,
            "degree":0.006622516556291391,
            "eigenvector":2.2762743141225855e-20,
            "group":6,
            "id":133,
            "name":"caadria2003_c5-1"
        },
        {
            "betweenness":0.0,
            "degree":0.006622516556291391,
            "eigenvector":4.242176492992784e-22,
            "group":2,
            "id":134,
            "name":"caadria2003_a1-3"
        },
        {
            "betweenness":4.88804793440555e-05,
            "degree":0.046357615894039736,
            "eigenvector":1.925821659455681e-07,
            "group":1,
            "id":135,
            "name":"519caadria2004"
        },
        {
            "betweenness":0.0,
            "degree":0.006622516556291391,
            "eigenvector":0.0014440527148702757,
            "group":7,
            "id":136,
            "name":"311caadria2004"
        },
        {
            "betweenness":0.0,
            "degree":0.006622516556291391,
            "eigenvector":4.242176492992784e-22,
            "group":24,
            "id":137,
            "name":"caadria2005_b_5c_b"
        },
        {
            "betweenness":0.0,
            "degree":0.006622516556291391,
            "eigenvector":4.242176492992784e-22,
            "group":22,
            "id":138,
            "name":"caadria2003_c4-2"
        },
        {
            "betweenness":0.0,
            "degree":0.013245033112582781,
            "eigenvector":1.5023482481305245e-13,
            "group":3,
            "id":139,
            "name":"caadria2003_a2-4"
        },
        {
            "betweenness":8.830022075055188e-05,
            "degree":0.013245033112582781,
            "eigenvector":3.219138006713675e-20,
            "group":6,
            "id":140,
            "name":"103caadria2004"
        },
        {
            "betweenness":0.0,
            "degree":0.006622516556291391,
            "eigenvector":1.7792977833265605e-15,
            "group":35,
            "id":141,
            "name":"513caadria2004"
        },
        {
            "betweenness":0.0,
            "degree":0.013245033112582781,
            "eigenvector":3.173923335039738e-18,
            "group":13,
            "id":142,
            "name":"305caadria2004"
        },
        {
            "betweenness":0.0,
            "degree":0.006622516556291391,
            "eigenvector":1.1478566049568635e-19,
            "group":0,
            "id":143,
            "name":"409caadria2004"
        },
        {
            "betweenness":0.0,
            "degree":0.006622516556291391,
            "eigenvector":4.242176492992784e-22,
            "group":20,
            "id":144,
            "name":"caadria2005_b_6a_c"
        },
        {
            "betweenness":2.4081878386514145e-05,
            "degree":0.033112582781456956,
            "eigenvector":5.577016846354064e-06,
            "group":8,
            "id":145,
            "name":"caadria2005_a_2c_d"
        },
        {
            "betweenness":2.4081878386514145e-05,
            "degree":0.033112582781456956,
            "eigenvector":5.577016846354064e-06,
            "group":8,
            "id":146,
            "name":"307caadria2004"
        },
        {
            "betweenness":4.88804793440555e-05,
            "degree":0.046357615894039736,
            "eigenvector":1.925821659455681e-07,
            "group":1,
            "id":147,
            "name":"303caadria2004"
        },
        {
            "betweenness":0.0012362030905077263,
            "degree":0.026490066225165563,
            "eigenvector":5.445494016733253e-13,
            "group":3,
            "id":148,
            "name":"caadria2005_b_4b_b"
        },
        {
            "betweenness":0.0,
            "degree":0.052980132450331126,
            "eigenvector":0.36614173954775114,
            "group":25,
            "id":149,
            "name":"caadria2005_a_2b_d"
        },
        {
            "betweenness":0.0,
            "degree":0.026490066225165563,
            "eigenvector":3.8552884191363995e-12,
            "group":3,
            "id":150,
            "name":"caadria2005_a_8c_d"
        },
        {
            "betweenness":0.00020309050772626935,
            "degree":0.052980132450331126,
            "eigenvector":0.31629069579293395,
            "group":25,
            "id":151,
            "name":"caadria2003_a4-2"
        }
    ]
}